Dockerfile
LICENSE
MANIFEST.in
README.rst
requirements.txt
setup.py
bin/radiopadre-http-server.py
bin/setup-radiopadre-virtualenv
icons/radiopadre-logo-32x32.png
icons/radiopadre-logo-64x64.png
icons/radiopadre-logo-long-200px.png
icons/radiopadre-logo-long-400px.png
icons/radiopadre-logo-long-600px.png
icons/radiopadre-logo-long-800px.png
icons/radiopadre-logo-with-text-200px.png
icons/radiopadre-logo-with-text-400px.png
icons/radiopadre-logo-with-text-600px.png
icons/radiopadre-logo-with-text.png
icons/radiopadre-logo.ico
icons/radiopadre-logo.png
js9-config/js9Prefs.json
js9-config/js9prefs.js
radiopadre/__init__.py
radiopadre/casatable.py
radiopadre/datadir.py
radiopadre/executor.py
radiopadre/file.py
radiopadre/filelist.py
radiopadre/fitsfile.py
radiopadre/htmlfile.py
radiopadre/imagefile.py
radiopadre/layouts.js
radiopadre/layouts.py
radiopadre/notebook.py
radiopadre/pdffile.py
radiopadre/render.py
radiopadre/settings_manager.py
radiopadre/table.py
radiopadre/term.py
radiopadre/textfile.py
radiopadre.egg-info/PKG-INFO
radiopadre.egg-info/SOURCES.txt
radiopadre.egg-info/dependency_links.txt
radiopadre.egg-info/entry_points.txt
radiopadre.egg-info/requires.txt
radiopadre.egg-info/top_level.txt
radiopadre/html/js9colormaps.js
radiopadre/html/js9partners.js
radiopadre/html/phantomjs-html-thumbnail.js
radiopadre/html/puppeteer-html-thumbnail.js
radiopadre/html/radiopadre-kernel.js
radiopadre/html/radiopadre-logo.ico
radiopadre/html/radiopadre.css
radiopadre/notebooks/radiopadre-default.ipynb
radiopadre/notebooks/radiopadre-tutorial.ipynb
radiopadre_kernel/__init__.py
radiopadre_kernel/js9/__init__.py
radiopadre_kernel/js9/js9-dualwindow-body-template.html
radiopadre_kernel/js9/js9-dualwindow-geometry-template.html
radiopadre_kernel/js9/js9-dualwindow-inline-geometry-template.html
radiopadre_kernel/js9/js9-dualwindow-tail-template.html
radiopadre_kernel/js9/js9-init-dynamic-template.html
radiopadre_kernel/js9/js9-init-static-template.html
radiopadre_kernel/js9/js9-singlewindow-body-template.html
radiopadre_kernel/js9/js9-singlewindow-tail-template.html
radiopadre_kernel/js9/js9-window-head-template.html
radiopadre_utils/__init__.py
radiopadre_utils/notebook_utils.py
