Metadata-Version: 2.1
Name: radiopadre
Version: 1.2.0
Summary: A data visualization framework for jupyter notebooks
Home-page: http://github.com/ratt-ru/radiopadre
Author: Oleg Smirnov
Author-email: osmirnov@gmail.com
License: MIT
Keywords: ipython notebook jupyter fits dataset resultset visualisation
Classifier: Development Status :: 5 - Production/Stable
Classifier: Topic :: Utilities
Classifier: License :: OSI Approved :: MIT License
Classifier: Programming Language :: Python :: 3
Classifier: Programming Language :: Python :: 3.7
Classifier: Programming Language :: Python :: 3.8
Requires-Python: >=3.7
Provides-Extra: casacore
License-File: LICENSE
